config/__init__.py
config/config.py
datasets/__init__.py
datasets/image_data_wrapper.py
datasets/image_dataset.py
dlcore/__init__.py
dlcore/config/__init__.py
dlcore/config/config.py
dlcore/datasets/__init__.py
dlcore/datasets/image_data_wrapper.py
dlcore/datasets/image_dataset.py
dlcore/evaluation/__init__.py
dlcore/evaluation/score_evaluation.py
dlcore/evaluation/score_fn.py
dlcore/evaluation/score_types.py
dlcore/evaluation/score_fn/__init__.py
dlcore/evaluation/score_fn/accuracy_score.py
dlcore/evaluation/score_fn/auc_score.py
dlcore/evaluation/score_fn/f1_score.py
dlcore/evaluation/score_fn/precision_score.py
dlcore/evaluation/score_fn/recall_score.py
dlcore/models/__init__.py
dlcore/models/nn_trainer.py
dlcore/models/cnn_image_classification/__init__.py
dlcore/models/cnn_image_classification/custom_cnn_image_classification.py
dlcore/models/cnn_image_classification/custom_cnn_image_classification_multylabel.py
dlcore/models/cnn_image_classification/cnn_backbone/__init__.py
dlcore/models/cnn_image_classification/cnn_backbone/cnn_backbone.py
dlcore/models/cnn_image_classification/cnn_backbone/cnn_layers.py
evaluation/__init__.py
evaluation/score_evaluation.py
evaluation/score_fn.py
evaluation/score_types.py
evaluation/score_fn/__init__.py
evaluation/score_fn/accuracy_score.py
evaluation/score_fn/auc_score.py
evaluation/score_fn/f1_score.py
evaluation/score_fn/precision_score.py
evaluation/score_fn/recall_score.py
services/__init__.py
services/dynamogram_service.py
dlcore-0.1.0.dist-info/METADATA
dlcore-0.1.0.dist-info/WHEEL
dlcore-0.1.0.dist-info/top_level.txt
dlcore-0.1.0.dist-info/RECORD
